tagui.py
tagui-1.6.3.dist-info/LICENSE.txt
tagui-1.6.3.dist-info/METADATA
tagui-1.6.3.dist-info/WHEEL
tagui-1.6.3.dist-info/top_level.txt
tagui-1.6.3.dist-info/RECORD
